barlibs/yahoo/__init__.py
barlibs/yahoo/engine.py
barlibs/yahoo/utils.py
bardata_yahoo-0.0.0.dist-info/METADATA
bardata_yahoo-0.0.0.dist-info/WHEEL
bardata_yahoo-0.0.0.dist-info/entry_points.txt
bardata_yahoo-0.0.0.dist-info/RECORD
