Metadata-Version: 2.4
Name: bardata-yahoo
Version: 0.0.0
Summary: Bardata engine for Yahoo Finance
License-Expression: MIT
Requires-Python: >=3.10
Requires-Dist: pandas
Requires-Dist: requests
Requires-Dist: yfinance
